cobaya_cosmo/__init__.py
cobaya_cosmo/generate_cosmo_likelihood_list.py
cobaya_cosmo/get.py
cobaya_cosmo/external/__init__.py
cobaya_cosmo/external/external_list.py
cobaya_cosmo-0.2.dist-info/LICENSE.txt
cobaya_cosmo-0.2.dist-info/METADATA
cobaya_cosmo-0.2.dist-info/WHEEL
cobaya_cosmo-0.2.dist-info/top_level.txt
cobaya_cosmo-0.2.dist-info/RECORD
