Metadata-Version: 2.1
Name: cobaya-cosmo
Version: 0.2
Summary: Cosmological codes, wrappers and links to external packages for the Cobaya package
Author: Jesus Torrado, Antony Lewis
Keywords: cosmology,inference,monte carlo,mcmc
Classifier: Development Status :: 5 - Production/Stable
Classifier: Operating System :: OS Independent
Classifier: Environment :: Console
Classifier: Intended Audience :: Science/Research
Classifier: Topic :: Scientific/Engineering :: Astronomy
Classifier: License :: OSI Approved :: GNU Lesser General Public License v3 (LGPLv3)
Classifier: Programming Language :: Python :: 3.8
Classifier: Programming Language :: Python :: 3.9
Classifier: Programming Language :: Python :: 3.10
Classifier: Programming Language :: Python :: 3.11
Classifier: Programming Language :: Python :: 3.12
Requires-Python: >=3.8.0
License-File: LICENSE.txt
